dicio/__init__.py
dicio/dicio.py
dicio/utils.py
dicio_scrapper-0.0.1.dist-info/LICENSE
dicio_scrapper-0.0.1.dist-info/METADATA
dicio_scrapper-0.0.1.dist-info/WHEEL
dicio_scrapper-0.0.1.dist-info/top_level.txt
dicio_scrapper-0.0.1.dist-info/RECORD
