Metadata-Version: 2.1
Name: dicio-scrapper
Version: 0.0.1
Summary: Unofficial Python API for Dicio based on the original API of Felipe Pontes.
Home-page: https://github.com/miloutsch/dicio
Author: Data & Analytics Research
Author-email: analytics.dar@take.net
License: MIT License
Platform: UNKNOWN
Classifier: Development Status :: 4 - Beta
Classifier: License :: OSI Approved :: MIT License
Classifier: Programming Language :: Python
Classifier: Programming Language :: Python :: 3 :: Only
Classifier: Topic :: Internet :: WWW/HTTP :: Browsers
Classifier: Topic :: Internet :: WWW/HTTP :: Indexing/Search
Classifier: Topic :: Utilities
